[
{
    "model": "auth.user",
    "pk": 1,
    "fields": {
        "password": "pbkdf2_sha256$100000$KoM4t892DJJo$ede48XrTfOgmlpuQ9+K299Dnz6ZkWqRrA3sFLpeJnhY=",
        "last_login": null,
        "is_superuser": false,
        "username": "farmer",
        "first_name": "old",
        "last_name": "mcdonald",
        "email": "farmer@dairyfarm.org",
        "is_staff": true,
        "is_active": true,
        "date_joined": "2018-03-26T21:10:17.911Z",
        "groups": [],
        "user_permissions": []
    }
},
{
    "model": "auth.user",
    "pk": 2,
    "fields": {
        "password": "pbkdf2_sha256$100000$oqrZkthZrP3N$OXzlTX95To0mvNUAyPsRjTZnv0E4psPwAtkB8Qz9FKA=",
        "last_login": null,
        "is_superuser": false,
        "username": "farmhand",
        "first_name": "mister",
        "last_name": "greenjeans",
        "email": "farmhand@dairyfarm.org",
        "is_staff": true,
        "is_active": true,
        "date_joined": "2018-03-26T21:10:18.319Z",
        "groups": [],
        "user_permissions": []
    }
},
{
    "model": "auth.user",
    "pk": 3,
    "fields": {
        "password": "pbkdf2_sha256$100000$GQr1L6Rx7xMj$X2MACoc4brRSV41D4R8P99wgTpnye1ds6G3oXvbo+MM=",
        "last_login": null,
        "is_superuser": false,
        "username": "vet",
        "first_name": "doctor",
        "last_name": "fixmeup",
        "email": "vet@dairyfarm.org",
        "is_staff": true,
        "is_active": true,
        "date_joined": "2018-03-26T21:10:18.713Z",
        "groups": [],
        "user_permissions": []
    }
}
]
